inigo
